aq_utilities/__init__.py
aq_utilities/config/__init__.py
aq_utilities/config/data.py
aq_utilities/data/__init__.py
aq_utilities/data/psql.py
aq_utilities/data/remote.py
aq_utilities/data/test_psql.py
aq_utilities/data/test_remote.py
aq_utilities/data/daily_stations/__init__.py
aq_utilities/data/daily_stations/psql.py
aq_utilities/data/failures/__init__.py
aq_utilities/data/failures/psql.py
aq_utilities/data/hourly_data/__init__.py
aq_utilities/data/hourly_data/psql.py
aq_utilities/data/processing/__init__.py
aq_utilities/data/processing/filter_stations.py
aq_utilities/data/processing/reindex.py
aq_utilities/data/stations_info/__init__.py
aq_utilities/data/stations_info/psql.py
aq_utilities/engine/__init__.py
aq_utilities/engine/psql.py
aq_utilities/engine/test_psql.py
aq_utilities-2024.7.14.4.dist-info/METADATA
aq_utilities-2024.7.14.4.dist-info/WHEEL
aq_utilities-2024.7.14.4.dist-info/licenses/LICENSE.md
aq_utilities-2024.7.14.4.dist-info/RECORD
